MANIFEST.in
README
setup.py
fabsetup_theno_termdown/__init__.py
fabsetup_theno_termdown/_version.py
fabsetup_theno_termdown/fabutils.py
fabsetup_theno_termdown.egg-info/PKG-INFO
fabsetup_theno_termdown.egg-info/SOURCES.txt
fabsetup_theno_termdown.egg-info/dependency_links.txt
fabsetup_theno_termdown.egg-info/requires.txt
fabsetup_theno_termdown.egg-info/top_level.txt
fabsetup_theno_termdown/files/home/USERNAME/bin/termdown.template