Metadata-Version: 1.1
Name: fabsetup-theno-termdown
Version: 0.1.3
Summary: Setup and install termdown
Home-page: https://github.com/theno/fabsetup-theno-termdown
Author: Theodor Nolte
Author-email: theno@gmx.net
License: MIT
Keywords: python development utilities library
Platform: UNKNOWN
Classifier: Development Status :: 3 - Alpha
Classifier: Intended Audience :: Developers
Classifier: Topic :: Software Development :: Libraries :: Python Modules
Classifier: License :: OSI Approved :: MIT License
Classifier: Programming Language :: Python :: 2
Classifier: Programming Language :: Python :: 2.6
Classifier: Programming Language :: Python :: 2.7
